indiweb/AsyncSystemCommand.py
indiweb/__init__.py
indiweb/database.py
indiweb/device.py
indiweb/driver.py
indiweb/indi_server.py
indiweb/main.py
indiweb/views/favicon.ico
indiweb/views/form.tpl
indiweb/views/css/bootstrap-select.min.css
indiweb/views/css/bootstrap.min.css
indiweb/views/css/jquery-ui.min.css
indiweb/views/css/schoolhouse.css
indiweb/views/fonts/glyphicons-halflings-regular.eot
indiweb/views/fonts/glyphicons-halflings-regular.svg
indiweb/views/fonts/glyphicons-halflings-regular.ttf
indiweb/views/fonts/glyphicons-halflings-regular.woff
indiweb/views/fonts/glyphicons-halflings-regular.woff2
indiweb/views/img/indi_logo.png
indiweb/views/img/space.jpg
indiweb/views/js/bootstrap-select.min.js
indiweb/views/js/bootstrap.min.js
indiweb/views/js/indi.js
indiweb/views/js/jquery-ui.min.js
indiweb/views/js/jquery.min.js
indiweb-0.2.0.dist-info/AUTHORS
indiweb-0.2.0.dist-info/LICENSE
indiweb-0.2.0.dist-info/METADATA
indiweb-0.2.0.dist-info/WHEEL
indiweb-0.2.0.dist-info/entry_points.txt
indiweb-0.2.0.dist-info/top_level.txt
indiweb-0.2.0.dist-info/RECORD
