Metadata-Version: 2.2
Name: indiweb
Version: 0.2.0
Summary: A simple web application to manage INDI server
Author-email: Jasem Mutlaq <mutlaqja@ikarustech.com>, Juan Menendez <juanmb@gmail.com>
License: LGPL
Project-URL: Homepage, http://www.indilib.org/
Classifier: License :: OSI Approved :: GNU Library or Lesser General Public License (LGPL)
Classifier: Natural Language :: English
Classifier: Programming Language :: Python
Classifier: Operating System :: OS Independent
Classifier: Intended Audience :: Science/Research
Classifier: Topic :: Scientific/Engineering :: Astronomy
Requires-Python: >=3.7
License-File: LICENSE
License-File: AUTHORS
Requires-Dist: requests==2.32.2
Requires-Dist: psutil==6.0.0
Requires-Dist: bottle==0.12.25
Requires-Dist: importlib_metadata==8.5.0
